phone_validator/__init__.py
genderapi_phone_validator-1.0.2.dist-info/LICENSE
genderapi_phone_validator-1.0.2.dist-info/METADATA
genderapi_phone_validator-1.0.2.dist-info/WHEEL
genderapi_phone_validator-1.0.2.dist-info/top_level.txt
genderapi_phone_validator-1.0.2.dist-info/RECORD
