Metadata-Version: 2.1
Name: genderapi-phone-validator
Version: 1.0.2
Summary: Official Python SDK for validating and formatting phone numbers using the GenderAPI.io service.
Author-email: Onur Ozturk <support@genderapi.io>
License: MIT
Project-URL: Homepage, https://www.genderapi.io
Project-URL: Documentation, https://www.genderapi.io/docs-phone-validation-formatter-api
Project-URL: Repository, https://github.com/GenderAPI/phone-validator-python
Project-URL: Issues, https://github.com/GenderAPI/phone-validator-python/issues
Keywords: gender,genderapi,phone validator,phone validation,phone number formatting,phone metadata,E.164,API client,python sdk
Classifier: Development Status :: 5 - Production/Stable
Classifier: Intended Audience :: Developers
Classifier: Topic :: Software Development :: Libraries :: Python Modules
Classifier: License :: OSI Approved :: MIT License
Classifier: Programming Language :: Python :: 3
Classifier: Programming Language :: Python :: 3.7
Classifier: Programming Language :: Python :: 3.8
Classifier: Programming Language :: Python :: 3.9
Classifier: Programming Language :: Python :: 3.10
Classifier: Programming Language :: Python :: 3.11
Classifier: Operating System :: OS Independent
Requires-Python: >=3.7
License-File: LICENSE
Requires-Dist: requests<3.0.0,>=2.28.0
